MANIFEST.in
README.md
setup.py
dash_treeview_antd/TreeView.py
dash_treeview_antd/__init__.py
dash_treeview_antd/_imports_.py
dash_treeview_antd/bundle.js
dash_treeview_antd/metadata.json
dash_treeview_antd/package.json
dash_treeview_antd.egg-info/PKG-INFO
dash_treeview_antd.egg-info/SOURCES.txt
dash_treeview_antd.egg-info/dependency_links.txt
dash_treeview_antd.egg-info/top_level.txt