Metadata-Version: 1.0
Name: dash-treeview-antd
Version: 0.0.1
Summary: Tree view component based on Ant Design widget.
Home-page: UNKNOWN
Author: kapot65@gmail.com
Author-email: UNKNOWN
License: MIT
Keywords: dash,plugin,treeview,plotly
Platform: UNKNOWN
